{
  "1": {
    "component_id": "1",
    "component_name": "Storage-main-36",
    "component_type": "Storage",
    "product_id": "4",
    "environment": "staging",
    "location": "EU-Central",
    "port_number": "5432",
    "operational_status": "offline",
    "created_at": "2025-05-11T13:21:46",
    "updated_at": "2025-07-26T05:21:46"
  },
  "2": {
    "component_id": "2",
    "component_name": "Network-backup-2",
    "component_type": "Network",
    "product_id": null,
    "environment": "production",
    "location": "US-East",
    "port_number": "6379",
    "operational_status": "degraded",
    "created_at": "2025-05-17T14:45:58",
    "updated_at": "2025-08-16T07:45:58"
  },
  "3": {
    "component_id": "3",
    "component_name": "Cache-primary-2",
    "component_type": "Cache",
    "product_id": "15",
    "environment": "development",
    "location": "US-West",
    "port_number": "80",
    "operational_status": "offline",
    "created_at": "2024-10-14T03:51:54",
    "updated_at": "2024-12-26T12:51:54"
  },
  "4": {
    "component_id": "4",
    "component_name": "Cache-primary-9",
    "component_type": "Cache",
    "product_id": null,
    "environment": "production",
    "location": "US-West",
    "port_number": "3306",
    "operational_status": "offline",
    "created_at": "2025-05-27T06:30:00",
    "updated_at": "2025-07-17T21:30:00"
  },
  "5": {
    "component_id": "5",
    "component_name": "Database-secondary-16",
    "component_type": "Database",
    "product_id": "20",
    "environment": "staging",
    "location": "UK-South",
    "port_number": "9000",
    "operational_status": "maintenance",
    "created_at": "2024-10-30T13:35:12",
    "updated_at": "2025-01-10T02:35:12"
  },
  "6": {
    "component_id": "6",
    "component_name": "Cache-backup-76",
    "component_type": "Cache",
    "product_id": "2",
    "environment": "production",
    "location": "US-West",
    "port_number": "5432",
    "operational_status": "offline",
    "created_at": "2025-03-10T12:54:19",
    "updated_at": "2025-05-03T21:54:19"
  },
  "7": {
    "component_id": "7",
    "component_name": "Database-secondary-31",
    "component_type": "Database",
    "product_id": null,
    "environment": "production",
    "location": "Asia-Pacific",
    "port_number": "27017",
    "operational_status": "maintenance",
    "created_at": "2025-06-11T00:36:29",
    "updated_at": "2025-07-03T17:36:29"
  },
  "8": {
    "component_id": "8",
    "component_name": "Application-primary-30",
    "component_type": "Application",
    "product_id": "15",
    "environment": "production",
    "location": "US-West",
    "port_number": "6379",
    "operational_status": "degraded",
    "created_at": "2025-05-13T09:39:58",
    "updated_at": "2025-06-19T07:39:58"
  },
  "9": {
    "component_id": "9",
    "component_name": "API-primary-70",
    "component_type": "API",
    "product_id": null,
    "environment": "development",
    "location": "US-West",
    "port_number": "443",
    "operational_status": "operational",
    "created_at": "2025-05-06T05:44:34",
    "updated_at": "2025-06-04T01:44:34"
  },
  "10": {
    "component_id": "10",
    "component_name": "Network-backup-77",
    "component_type": "Network",
    "product_id": "15",
    "environment": "development",
    "location": "Asia-Pacific",
    "port_number": "6379",
    "operational_status": "maintenance",
    "created_at": "2025-04-19T18:08:03",
    "updated_at": "2025-07-01T03:08:03"
  },
  "11": {
    "component_id": "11",
    "component_name": "Cache-primary-77",
    "component_type": "Cache",
    "product_id": "20",
    "environment": "development",
    "location": "US-East",
    "port_number": "443",
    "operational_status": "degraded",
    "created_at": "2025-01-29T14:13:36",
    "updated_at": "2025-02-04T03:13:36"
  },
  "12": {
    "component_id": "12",
    "component_name": "Server-backup-74",
    "component_type": "Server",
    "product_id": "15",
    "environment": "development",
    "location": "US-West",
    "port_number": "9000",
    "operational_status": "maintenance",
    "created_at": "2025-09-26T17:32:23",
    "updated_at": "2025-10-01T22:32:23"
  },
  "13": {
    "component_id": "13",
    "component_name": "Database-main-45",
    "component_type": "Database",
    "product_id": "4",
    "environment": "staging",
    "location": "EU-Central",
    "port_number": "9000",
    "operational_status": "maintenance",
    "created_at": "2025-01-07T23:57:30",
    "updated_at": "2025-03-01T09:57:30"
  },
  "14": {
    "component_id": "14",
    "component_name": "Application-main-98",
    "component_type": "Application",
    "product_id": "11",
    "environment": "development",
    "location": "EU-Central",
    "port_number": "443",
    "operational_status": "maintenance",
    "created_at": "2024-12-17T01:16:47",
    "updated_at": "2025-02-25T02:16:47"
  },
  "15": {
    "component_id": "15",
    "component_name": "Server-replica-60",
    "component_type": "Server",
    "product_id": null,
    "environment": "development",
    "location": "UK-South",
    "port_number": "27017",
    "operational_status": "maintenance",
    "created_at": "2025-06-15T19:44:40",
    "updated_at": "2025-08-06T20:44:40"
  },
  "16": {
    "component_id": "16",
    "component_name": "Server-secondary-35",
    "component_type": "Server",
    "product_id": "15",
    "environment": "testing",
    "location": "US-East",
    "port_number": "80",
    "operational_status": "degraded",
    "created_at": "2025-07-03T20:50:15",
    "updated_at": "2025-09-12T00:50:15"
  },
  "17": {
    "component_id": "17",
    "component_name": "Network-backup-71",
    "component_type": "Network",
    "product_id": "8",
    "environment": "production",
    "location": "Asia-Pacific",
    "port_number": "443",
    "operational_status": "degraded",
    "created_at": "2025-01-28T17:51:07",
    "updated_at": "2025-01-30T10:51:07"
  },
  "18": {
    "component_id": "18",
    "component_name": "Cache-backup-66",
    "component_type": "Cache",
    "product_id": "16",
    "environment": "testing",
    "location": "US-West",
    "port_number": "27017",
    "operational_status": "degraded",
    "created_at": "2024-12-30T10:09:37",
    "updated_at": "2025-03-30T18:09:37"
  },
  "19": {
    "component_id": "19",
    "component_name": "API-secondary-77",
    "component_type": "API",
    "product_id": "3",
    "environment": "development",
    "location": "Asia-Pacific",
    "port_number": "8080",
    "operational_status": "offline",
    "created_at": "2025-01-09T21:09:10",
    "updated_at": "2025-03-16T20:09:10"
  },
  "20": {
    "component_id": "20",
    "component_name": "Server-backup-93",
    "component_type": "Server",
    "product_id": "16",
    "environment": "staging",
    "location": "Asia-Pacific",
    "port_number": "27017",
    "operational_status": "offline",
    "created_at": "2025-03-01T10:26:15",
    "updated_at": "2025-04-09T04:26:15"
  },
  "21": {
    "component_id": "21",
    "component_name": "Service-replica-98",
    "component_type": "Service",
    "product_id": "11",
    "environment": "staging",
    "location": "US-West",
    "port_number": "9000",
    "operational_status": "degraded",
    "created_at": "2024-11-18T13:19:12",
    "updated_at": "2025-01-27T01:19:12"
  },
  "22": {
    "component_id": "22",
    "component_name": "API-primary-41",
    "component_type": "API",
    "product_id": "13",
    "environment": "testing",
    "location": "US-West",
    "port_number": "27017",
    "operational_status": "operational",
    "created_at": "2025-06-16T14:03:09",
    "updated_at": "2025-08-16T12:03:09"
  },
  "23": {
    "component_id": "23",
    "component_name": "Network-replica-76",
    "component_type": "Network",
    "product_id": "15",
    "environment": "production",
    "location": "UK-South",
    "port_number": "27017",
    "operational_status": "operational",
    "created_at": "2025-06-06T09:56:58",
    "updated_at": "2025-07-18T12:56:58"
  },
  "24": {
    "component_id": "24",
    "component_name": "Network-main-84",
    "component_type": "Network",
    "product_id": "9",
    "environment": "development",
    "location": "UK-South",
    "port_number": "9000",
    "operational_status": "operational",
    "created_at": "2025-01-23T05:37:17",
    "updated_at": "2025-02-11T07:37:17"
  },
  "25": {
    "component_id": "25",
    "component_name": "Service-replica-49",
    "component_type": "Service",
    "product_id": "16",
    "environment": "production",
    "location": "UK-South",
    "port_number": "443",
    "operational_status": "degraded",
    "created_at": "2025-03-25T07:05:16",
    "updated_at": "2025-05-05T03:05:16"
  },
  "26": {
    "component_id": "26",
    "component_name": "Application-secondary-96",
    "component_type": "Application",
    "product_id": "4",
    "environment": "testing",
    "location": "US-West",
    "port_number": "6379",
    "operational_status": "operational",
    "created_at": "2025-01-29T12:25:52",
    "updated_at": "2025-02-10T01:25:52"
  },
  "27": {
    "component_id": "27",
    "component_name": "Server-backup-8",
    "component_type": "Server",
    "product_id": "5",
    "environment": "staging",
    "location": "UK-South",
    "port_number": "9000",
    "operational_status": "degraded",
    "created_at": "2025-09-24T12:31:28",
    "updated_at": "2025-10-31T23:31:28"
  },
  "28": {
    "component_id": "28",
    "component_name": "Network-secondary-11",
    "component_type": "Network",
    "product_id": "8",
    "environment": "testing",
    "location": "UK-South",
    "port_number": "3306",
    "operational_status": "degraded",
    "created_at": "2025-07-17T17:19:51",
    "updated_at": "2025-10-04T05:19:51"
  },
  "29": {
    "component_id": "29",
    "component_name": "Cache-backup-59",
    "component_type": "Cache",
    "product_id": null,
    "environment": "testing",
    "location": "EU-Central",
    "port_number": "3306",
    "operational_status": "operational",
    "created_at": "2025-09-27T03:07:18",
    "updated_at": "2025-10-30T00:07:18"
  },
  "30": {
    "component_id": "30",
    "component_name": "Cache-backup-655",
    "component_type": "Cache",
    "product_id": "10",
    "environment": "staging",
    "location": "Asia-Pacific",
    "port_number": "27017",
    "operational_status": "operational",
    "created_at": "2024-10-26T21:35:49",
    "updated_at": "2024-12-20T19:35:49"
  }
}